PingDing/PingDing.py
PingDing/__init__.py
PingDing-0.0.0.dist-info/LICENSE
PingDing-0.0.0.dist-info/METADATA
PingDing-0.0.0.dist-info/WHEEL
PingDing-0.0.0.dist-info/entry_points.txt
PingDing-0.0.0.dist-info/top_level.txt
PingDing-0.0.0.dist-info/RECORD
