Metadata-Version: 2.1
Name: PingDing
Version: 0.0.0
Summary: Graphically show ping result of various nodes
Home-page: https://github.com/Troepje/PingDing
Author: Troepje
Author-email: 
License-File: LICENSE
Requires-Dist: argparse
